pyfs_auth/__init__.py
pyfs_auth/app_access_token.py
pyfs_auth/app_access_token_internal.py
pyfs_auth/app_ticket.py
pyfs_auth/authen.py
pyfs_auth/basetoken.py
pyfs_auth/oauth2.py
pyfs_auth/tenant_access_token.py
pyfs_auth/tenant_access_token_internal.py
pyfs_auth-1.0.12.dist-info/METADATA
pyfs_auth-1.0.12.dist-info/WHEEL
pyfs_auth-1.0.12.dist-info/top_level.txt
pyfs_auth-1.0.12.dist-info/RECORD
